README.md
setup.cfg
setup.py
ShutTUM/__init__.py
ShutTUM/devices.py
ShutTUM/sequence.py
ShutTUM/values.py
ShutTUM.egg-info/PKG-INFO
ShutTUM.egg-info/SOURCES.txt
ShutTUM.egg-info/dependency_links.txt
ShutTUM.egg-info/requires.txt
ShutTUM.egg-info/top_level.txt