Metadata-Version: 1.1
Name: ShutTUM
Version: 1.1
Summary: A utility API to easily interact with the ShutTUM dataset
Home-page: https://github.com/gollth/ShutTUM
Author: Thore Goll
Author-email: thoregoll@googlemail.de
License: MIT
Keywords: dataset rolling shutter visual odometry slam
Platform: UNKNOWN
Classifier: Development Status :: 5 - Production/Stable
Classifier: Intended Audience :: Developers
Classifier: Topic :: Software Development :: Localization
Classifier: Programming Language :: Python :: 2.7
Classifier: Programming Language :: Python :: 3
Classifier: Programming Language :: Python :: 3.6
